highlight_io/__init__.py
highlight_io/integrations/__init__.py
highlight_io/integrations/all.py
highlight_io/integrations/anthropic.py
highlight_io/integrations/aws.py
highlight_io/integrations/azure.py
highlight_io/integrations/bedrock.py
highlight_io/integrations/boto.py
highlight_io/integrations/boto3sqs.py
highlight_io/integrations/celery.py
highlight_io/integrations/chromadb.py
highlight_io/integrations/cohere.py
highlight_io/integrations/django.py
highlight_io/integrations/fastapi.py
highlight_io/integrations/flask.py
highlight_io/integrations/gcp.py
highlight_io/integrations/haystack.py
highlight_io/integrations/langchain.py
highlight_io/integrations/llamaindex.py
highlight_io/integrations/openai.py
highlight_io/integrations/pinecone.py
highlight_io/integrations/qdrant.py
highlight_io/integrations/redis.py
highlight_io/integrations/replicate.py
highlight_io/integrations/requests.py
highlight_io/integrations/serverless.py
highlight_io/integrations/sqlalchemy.py
highlight_io/integrations/transformers.py
highlight_io/integrations/vertexai.py
highlight_io/integrations/watsonx.py
highlight_io/integrations/weaviate.py
highlight_io/sdk.py
highlight_io/utils/__init__.py
highlight_io/utils/dict.py
highlight_io/utils/lru_cache.py
highlight_io-0.10.2.dist-info/METADATA
highlight_io-0.10.2.dist-info/WHEEL
highlight_io-0.10.2.dist-info/RECORD
